odoo/addons/crm_timesheet/README.rst
odoo/addons/crm_timesheet/__init__.py
odoo/addons/crm_timesheet/__manifest__.py
odoo/addons/crm_timesheet/i18n/crm_timesheet.pot
odoo/addons/crm_timesheet/i18n/cs_CZ.po
odoo/addons/crm_timesheet/i18n/de.po
odoo/addons/crm_timesheet/i18n/es.po
odoo/addons/crm_timesheet/i18n/fr.po
odoo/addons/crm_timesheet/i18n/it.po
odoo/addons/crm_timesheet/i18n/nl.po
odoo/addons/crm_timesheet/i18n/pt.po
odoo/addons/crm_timesheet/i18n/pt_BR.po
odoo/addons/crm_timesheet/models/__init__.py
odoo/addons/crm_timesheet/models/account_analytic_line.py
odoo/addons/crm_timesheet/models/crm_lead.py
odoo/addons/crm_timesheet/readme/CONTRIBUTORS.md
odoo/addons/crm_timesheet/readme/DESCRIPTION.md
odoo/addons/crm_timesheet/readme/ROADMAP.md
odoo/addons/crm_timesheet/readme/USAGE.md
odoo/addons/crm_timesheet/security/ir.model.access.csv
odoo/addons/crm_timesheet/static/description/icon.png
odoo/addons/crm_timesheet/static/description/index.html
odoo/addons/crm_timesheet/tests/__init__.py
odoo/addons/crm_timesheet/tests/test_account_analytic_line.py
odoo/addons/crm_timesheet/views/crm_lead_view.xml
odoo/addons/crm_timesheet/views/hr_timesheet_view.xml
odoo/addons/crm_timesheet/wizards/__init__.py
odoo/addons/crm_timesheet/wizards/hr_timesheet_switch.py
odoo_addon_crm_timesheet-18.0.1.0.0.2.dist-info/METADATA
odoo_addon_crm_timesheet-18.0.1.0.0.2.dist-info/WHEEL
odoo_addon_crm_timesheet-18.0.1.0.0.2.dist-info/top_level.txt
odoo_addon_crm_timesheet-18.0.1.0.0.2.dist-info/RECORD
